treasury_prime_client/__init__.py
treasury_prime_client/api/__init__.py
treasury_prime_client/api/account_application_api.py
treasury_prime_client/api/account_opening_api.py
treasury_prime_client/api/accounts_api.py
treasury_prime_client/api/ach_api.py
treasury_prime_client/api/additional_person_application_api.py
treasury_prime_client/api/average_balance_api.py
treasury_prime_client/api/bill_pay_api.py
treasury_prime_client/api/book_api.py
treasury_prime_client/api/business_api.py
treasury_prime_client/api/business_application_api.py
treasury_prime_client/api/card_auth_loop_endpoint_api.py
treasury_prime_client/api/card_charge_api.py
treasury_prime_client/api/card_event_api.py
treasury_prime_client/api/card_product_api.py
treasury_prime_client/api/cards_api.py
treasury_prime_client/api/check_deposit_api.py
treasury_prime_client/api/check_image_api.py
treasury_prime_client/api/check_issuing_api.py
treasury_prime_client/api/counterparties_api.py
treasury_prime_client/api/daily_balance_api.py
treasury_prime_client/api/default_api.py
treasury_prime_client/api/deposit_api.py
treasury_prime_client/api/digital_wallet_tokens_api.py
treasury_prime_client/api/document_api.py
treasury_prime_client/api/file_upload_api.py
treasury_prime_client/api/incoming_wire_api.py
treasury_prime_client/api/kyc_api.py
treasury_prime_client/api/kyc_product_api.py
treasury_prime_client/api/marqeta_js_api.py
treasury_prime_client/api/payments_api.py
treasury_prime_client/api/person_api.py
treasury_prime_client/api/person_application_api.py
treasury_prime_client/api/reserve_api.py
treasury_prime_client/api/routing_number_api.py
treasury_prime_client/api/search_api.py
treasury_prime_client/api/settings_api.py
treasury_prime_client/api/simulations_api.py
treasury_prime_client/api/statement_api.py
treasury_prime_client/api/transaction_api.py
treasury_prime_client/api/utilities_api.py
treasury_prime_client/api/webhooks_api.py
treasury_prime_client/api/wire_api.py
treasury_prime_client-1.13.548.dist-info/WHEEL
treasury_prime_client-1.13.548.dist-info/METADATA
treasury_prime_client-1.13.548.dist-info/RECORD
