Metadata-Version: 2.1
Name: treasury-prime-client
Version: 1.13.548
Summary: Treasury Prime API Client generated by openapi-generator
Author: Swadesh
Author-email: dev@swadesh.co
Maintainer: D. Kasi Pavan Kumar
Maintainer-email: kasi@swadesh.co
Requires-Python: >=3.6,<4.0
Classifier: Programming Language :: Python :: 3
Classifier: Programming Language :: Python :: 3.6
Classifier: Programming Language :: Python :: 3.7
Classifier: Programming Language :: Python :: 3.8
Classifier: Programming Language :: Python :: 3.9
Classifier: Programming Language :: Python :: 3.10
Classifier: Programming Language :: Python :: 3.11
Requires-Dist: python-dateutil (>=2.5.3,<3.0.0)
Requires-Dist: urllib3 (>=1.25.3,<2.0.0)
